protestr/__about__.py
protestr/__init__.py
protestr/_provider.py
protestr/_resolver.py
protestr/_specs.py
protestr/specs.py
protestr-4.1.3.dist-info/METADATA
protestr-4.1.3.dist-info/WHEEL
protestr-4.1.3.dist-info/licenses/LICENSE
protestr-4.1.3.dist-info/RECORD
