Metadata-Version: 2.4
Name: protestr
Version: 4.1.3
Summary: Pro Test Fixture Provider
Project-URL: Homepage, https://github.com/Grimmscorpp/protestr
Project-URL: Documentation, https://github.com/Grimmscorpp/protestr?tab=readme-ov-file#documentation
Project-URL: Issues, https://github.com/Grimmscorpp/protestr/issues
Project-URL: Source, https://github.com/Grimmscorpp/protestr
Author-email: Ikram Khan <ikramkhanfahim@gmail.com>
License-Expression: MIT
License-File: LICENSE
Keywords: dependency,fixture,inject,spec,specification,teardown,test
Classifier: License :: OSI Approved :: MIT License
Classifier: Operating System :: OS Independent
Classifier: Programming Language :: Python :: 3.10
Classifier: Programming Language :: Python :: 3.11
Classifier: Programming Language :: Python :: 3.12
Classifier: Programming Language :: Python :: 3.13
Classifier: Programming Language :: Python :: 3.14
Classifier: Programming Language :: Python :: Implementation :: CPython
Classifier: Programming Language :: Python :: Implementation :: PyPy
Requires-Python: >=3.10
